{
  "id": "a48d9573-a9d9-47b0-b6e0-70f381228de7",
  "prevId": "00000000-0000-0000-0000-000000000000",
  "version": "7",
  "dialect": "postgresql",
  "tables": {
    "public.transactions": {
      "name": "transactions",
      "schema": "",
      "columns": {
        "id": {
          "name": "id",
          "type": "uuid",
          "primaryKey": false,
          "notNull": false,
          "default": "gen_random_uuid()"
        },
        "txnid": {
          "name": "txnid",
          "type": "text",
          "primaryKey": false,
          "notNull": true
        },
        "refno": {
          "name": "refno",
          "type": "text",
          "primaryKey": false,
          "notNull": true
        },
        "dateCreated": {
          "name": "dateCreated",
          "type": "timestamp",
          "primaryKey": false,
          "notNull": false,
          "default": "now()"
        },
        "dateUpdated": {
          "name": "dateUpdated",
          "type": "timestamp",
          "primaryKey": false,
          "notNull": false
        }
      },
      "indexes": {
        "txnid_index": {
          "name": "txnid_index",
          "columns": [
            {
              "expression": "txnid",
              "isExpression": false,
              "asc": true,
              "nulls": "last"
            }
          ],
          "isUnique": false,
          "concurrently": false,
          "method": "btree",
          "with": {}
        },
        "refno_index": {
          "name": "refno_index",
          "columns": [
            {
              "expression": "refno",
              "isExpression": false,
              "asc": true,
              "nulls": "last"
            }
          ],
          "isUnique": false,
          "concurrently": false,
          "method": "btree",
          "with": {}
        }
      },
      "foreignKeys": {},
      "compositePrimaryKeys": {},
      "uniqueConstraints": {
        "transactions_txnid_unique": {
          "name": "transactions_txnid_unique",
          "nullsNotDistinct": false,
          "columns": [
            "txnid"
          ]
        },
        "transactions_refno_unique": {
          "name": "transactions_refno_unique",
          "nullsNotDistinct": false,
          "columns": [
            "refno"
          ]
        }
      },
      "policies": {},
      "checkConstraints": {},
      "isRLSEnabled": false
    }
  },
  "enums": {},
  "schemas": {},
  "sequences": {},
  "roles": {},
  "policies": {},
  "views": {},
  "_meta": {
    "columns": {},
    "schemas": {},
    "tables": {}
  }
}